namekox_amqp/__init__.py
namekox_amqp/constants.py
namekox_amqp/exceptions.py
namekox_amqp/cli/__init__.py
namekox_amqp/cli/subctx/__init__.py
namekox_amqp/cli/subctx/amqppub.py
namekox_amqp/cli/subctx/amqprpc.py
namekox_amqp/core/__init__.py
namekox_amqp/core/connection.py
namekox_amqp/core/consumer.py
namekox_amqp/core/messaging.py
namekox_amqp/core/producer.py
namekox_amqp/core/proxy.py
namekox_amqp/core/dependencies/__init__.py
namekox_amqp/core/dependencies/pub/__init__.py
namekox_amqp/core/dependencies/rpc/__init__.py
namekox_amqp/core/dependencies/rpc/consumer.py
namekox_amqp/core/dependencies/rpc/listener.py
namekox_amqp/core/dependencies/rpc/rpcproxy.py
namekox_amqp/core/dependencies/rpc/rspproxy.py
namekox_amqp/core/entrypoints/__init__.py
namekox_amqp/core/entrypoints/consumer.py
namekox_amqp/core/entrypoints/rpc/__init__.py
namekox_amqp/core/entrypoints/rpc/consumer.py
namekox_amqp/core/entrypoints/rpc/handler.py
namekox_amqp/core/entrypoints/rpc/producer.py
namekox_amqp/core/entrypoints/rpc/response.py
namekox_amqp/core/entrypoints/sub/__init__.py
namekox_amqp/core/entrypoints/sub/consumer.py
namekox_amqp/core/entrypoints/sub/handler.py
namekox_amqp/core/standalone/__init__.py
namekox_amqp/core/standalone/pub.py
namekox_amqp/core/standalone/rpc.py
namekox_amqp-0.0.18.dist-info/LICENSE
namekox_amqp-0.0.18.dist-info/METADATA
namekox_amqp-0.0.18.dist-info/WHEEL
namekox_amqp-0.0.18.dist-info/top_level.txt
namekox_amqp-0.0.18.dist-info/zip-safe
namekox_amqp-0.0.18.dist-info/RECORD
